odoo/addons/partner_code_program/README.rst
odoo/addons/partner_code_program/__init__.py
odoo/addons/partner_code_program/__manifest__.py
odoo/addons/partner_code_program/hooks.py
odoo/addons/partner_code_program/i18n/es.po
odoo/addons/partner_code_program/models/__init__.py
odoo/addons/partner_code_program/models/res_partner.py
odoo/addons/partner_code_program/models/res_partner_code_program.py
odoo/addons/partner_code_program/models/res_partner_code_program_mixin.py
odoo/addons/partner_code_program/readme/CONTRIBUTORS.md
odoo/addons/partner_code_program/readme/DESCRIPTION.md
odoo/addons/partner_code_program/readme/USAGE.md
odoo/addons/partner_code_program/security/ir.model.access.csv
odoo/addons/partner_code_program/static/description/icon.png
odoo/addons/partner_code_program/static/description/index.html
odoo/addons/partner_code_program/tests/__init__.py
odoo/addons/partner_code_program/tests/test_partner_code_program.py
odoo/addons/partner_code_program/views/res_partner_code_program_views.xml
odoo/addons/partner_code_program/views/res_partner_views.xml
odoo_addon_partner_code_program-18.0.1.0.0.1.dist-info/METADATA
odoo_addon_partner_code_program-18.0.1.0.0.1.dist-info/WHEEL
odoo_addon_partner_code_program-18.0.1.0.0.1.dist-info/top_level.txt
odoo_addon_partner_code_program-18.0.1.0.0.1.dist-info/RECORD
